txl_local_contents/__init__.py
txl_local_contents/main.py
txl_local_contents-0.3.6.dist-info/METADATA
txl_local_contents-0.3.6.dist-info/WHEEL
txl_local_contents-0.3.6.dist-info/entry_points.txt
txl_local_contents-0.3.6.dist-info/licenses/LICENSE.txt
txl_local_contents-0.3.6.dist-info/RECORD
