Metadata-Version: 2.4
Name: txl_local_contents
Version: 0.3.6
Summary: TXL plugin for local contents
Project-URL: Source, https://github.com/davidbrochart/jpterm/plugins/local_contents
Author-email: David Brochart <david.brochart@gmail.com>
License-Expression: MIT
License-File: LICENSE.txt
Classifier: Development Status :: 4 - Beta
Classifier: Programming Language :: Python
Classifier: Programming Language :: Python :: 3.10
Classifier: Programming Language :: Python :: 3.11
Classifier: Programming Language :: Python :: 3.12
Classifier: Programming Language :: Python :: 3.13
Classifier: Programming Language :: Python :: Implementation :: CPython
Classifier: Programming Language :: Python :: Implementation :: PyPy
Requires-Python: >=3.10
Requires-Dist: anyio<5,>=3.7.0
Requires-Dist: jupyter-ydoc<4.0.0,>=3.0.2
Requires-Dist: txl==0.3.2
